fastsdr/__init__.py
fastsdr/fastsdr.py
fastsdr-0.0.3.dist-info/LICENSE
fastsdr-0.0.3.dist-info/METADATA
fastsdr-0.0.3.dist-info/WHEEL
fastsdr-0.0.3.dist-info/top_level.txt
fastsdr-0.0.3.dist-info/RECORD
