Metadata-Version: 2.1
Name: fastsdr
Version: 0.0.3
Summary: A faster way to calculate SDR
Author-email: Blanc <Jerry.Tobing@binus.ac.id>
Project-URL: Homepage, https://github.com/b-lanc/fastsdr
License-File: LICENSE
